rest_object
