Metadata-Version: 1.1
Name: rest-object
Version: 2.2.2
Summary: Create a REST API from any model you want thank your serializer. You can decide If you want an Authorization and if your datas are linked to an account.
Home-page: https://github.com/zephirdeadline/djangoAPI_rest_object
Author: Melvyn Petrocchi
Author-email: w4pity@gmail.com
License: WTFPL
Platform: UNKNOWN
Classifier: Programming Language :: Python
Classifier: Development Status :: 4 - Beta
Classifier: License :: OSI Approved
Classifier: Natural Language :: French
Classifier: Operating System :: OS Independent
Classifier: Programming Language :: Python :: 3.6
Classifier: Topic :: Software Development :: Libraries :: Python Modules
